{
	"name": "PL_Interview_CopySpecificColumData",
	"properties": {
		"activities": [
			{
				"name": "Copy data1",
				"type": "Copy",
				"dependsOn": [],
				"policy": {
					"timeout": "0.12:00:00",
					"retry": 0,
					"retryIntervalInSeconds": 30,
					"secureOutput": false,
					"secureInput": false
				},
				"userProperties": [],
				"typeProperties": {
					"source": {
						"type": "DelimitedTextSource",
						"storeSettings": {
							"type": "AzureBlobStorageReadSettings",
							"recursive": true,
							"enablePartitionDiscovery": false
						},
						"formatSettings": {
							"type": "DelimitedTextReadSettings"
						}
					},
					"sink": {
						"type": "DelimitedTextSink",
						"storeSettings": {
							"type": "AzureBlobStorageWriteSettings"
						},
						"formatSettings": {
							"type": "DelimitedTextWriteSettings",
							"quoteAllText": true,
							"fileExtension": ".txt"
						}
					},
					"enableStaging": false,
					"translator": {
						"type": "TabularTranslator",
						"mappings": [
							{
								"source": {
									"name": "Car_Name",
									"type": "String",
									"physicalType": "String"
								},
								"sink": {
									"name": "Car_Name",
									"type": "String",
									"physicalType": "String"
								}
							},
							{
								"source": {
									"name": "Transmission",
									"type": "String",
									"physicalType": "String"
								},
								"sink": {
									"name": "Transmission",
									"type": "String",
									"physicalType": "String"
								}
							},
							{
								"source": {
									"name": "Selling_Price",
									"type": "String",
									"physicalType": "String"
								},
								"sink": {
									"name": "Selling_Price",
									"type": "String",
									"physicalType": "String"
								}
							}
						],
						"typeConversion": true,
						"typeConversionSettings": {
							"allowDataTruncation": true,
							"treatBooleanAsNumber": false
						}
					}
				},
				"inputs": [
					{
						"referenceName": "DelimitedText1",
						"type": "DatasetReference"
					}
				],
				"outputs": [
					{
						"referenceName": "DelimitedText2",
						"type": "DatasetReference"
					}
				]
			}
		],
		"annotations": [],
		"lastPublishTime": "2024-02-23T09:45:22Z"
	},
	"type": "Microsoft.DataFactory/factories/pipelines"
}